{"assets":{"AEDB02A577FFF3DD06535D082E02A16F":{"type":"texture","index":153,"assetRequest":{"type":"slide","state":"incoming","slide":"4C2970CF-F56A-4F14-9F32-C94F16E467DF"},"url":"assets/AEDB02A577FFF3DD06535D082E02A16F.svg","width":1600,"height":900},"7EB294B38CCD0E207FFE294CDDE637E3":{"type":"texture","index":152,"assetRequest":{"type":"slide","state":"outgoing","slide":"6CA62946-60C2-4AB7-875E-DE7E2131C054"},"url":"assets/7EB294B38CCD0E207FFE294CDDE637E3.svg","width":1600,"height":900}},"events":[{"effects":[{"beginTime":0,"baseLayer":{"animations":[],"initialState":{"affineTransform":[1,0,0,1,0,0],"masksToBounds":true,"rotation":0,"scale":1,"position":{"pointX":800,"pointY":450},"width":1600,"sublayerTransform":[1,0,0,0,0,1,0,0,0,0,1,0,0,0,0,1],"contentsRect":{"y":0,"x":0,"width":1,"height":1},"opacity":1,"edgeAntialiasingMask":0,"height":900,"hidden":false,"anchorPoint":{"pointX":0.5,"pointY":0.5}},"objectID":"0","layers":[{"animations":[],"initialState":{"affineTransform":[1,0,0,1,0,0],"masksToBounds":false,"rotation":0,"scale":1,"position":{"pointX":800,"pointY":450},"width":1600,"sublayerTransform":[1,0,0,0,0,1,0,0,0,0,1,-0.0004200949496013118,0,0,0,1],"contentsRect":{"y":0,"x":0,"width":1,"height":1},"opacity":1,"edgeAntialiasingMask":15,"height":900,"hidden":false,"anchorPoint":{"pointX":0.5,"pointY":0.5}},"layers":[{"animations":[],"layers":[],"initialState":{"affineTransform":[1,0,0,1,0,0],"masksToBounds":false,"rotation":0,"scale":1,"position":{"pointX":800,"pointY":450},"width":1600,"sublayerTransform":[1,0,0,0,0,1,0,0,0,0,1,0,0,0,0,1],"contentsRect":{"y":0,"x":0,"width":1,"height":1},"opacity":1,"edgeAntialiasingMask":0,"height":900,"hidden":false,"anchorPoint":{"pointX":0.5,"pointY":0.5}},"texture":"AEDB02A577FFF3DD06535D082E02A16F"},{"animations":[{"from":{"scalar":false},"beginTime":0,"repeatCount":0,"fillMode":"both","property":"hidden","duration":0.01,"to":{"scalar":true}}],"layers":[],"initialState":{"affineTransform":[1,0,0,1,0,0],"masksToBounds":false,"rotation":0,"scale":1,"position":{"pointX":800,"pointY":450},"width":1600,"sublayerTransform":[1,0,0,0,0,1,0,0,0,0,1,0,0,0,0,1],"contentsRect":{"y":0,"x":0,"width":1,"height":1},"opacity":1,"edgeAntialiasingMask":0,"height":900,"hidden":false,"anchorPoint":{"pointX":0.5,"pointY":0.5}},"texture":"7EB294B38CCD0E207FFE294CDDE637E3"}]}]},"effects":[],"duration":0.01,"type":"transition","name":"none","objectID":"0"}],"automaticPlay":false,"hyperlinks":[{"url":"http://www.paciellogroup.com/blog/2014/09/web-components-punch-list/","targetRectangle":{"y":835.5,"x":22,"width":764.4375,"height":29}}],"accessibility":[{"text":"http://www.paciellogroup.com/blog/2014/09/web-components-punch-list/","targetRectangle":{"y":835.5,"x":22,"width":764.4375,"height":29}},{"text":"￼","targetRectangle":{"y":854.9642333984375,"x":1487.229248046875,"width":22.763671875,"height":21}},{"text":"Steve Faulkner’s checklist for custom components and web components is a good baseline for accessibility standards","targetRectangle":{"y":256.0833282470703,"x":136,"width":1356.12,"height":216}},{"text":"GDS","targetRectangle":{"y":826,"x":1418.986328125,"width":91.013671875,"height":50}}],"baseLayer":{"animations":[],"initialState":{"affineTransform":[1,0,0,1,0,0],"masksToBounds":true,"rotation":0,"scale":1,"position":{"pointX":800,"pointY":450},"width":1600,"sublayerTransform":[1,0,0,0,0,1,0,0,0,0,1,0,0,0,0,1],"contentsRect":{"y":0,"x":0,"width":1,"height":1},"opacity":1,"edgeAntialiasingMask":0,"height":900,"hidden":false,"anchorPoint":{"pointX":0.5,"pointY":0.5}},"objectID":"0","layers":[{"animations":[],"initialState":{"affineTransform":[1,0,0,1,0,0],"masksToBounds":false,"rotation":0,"scale":1,"position":{"pointX":800,"pointY":450},"width":1600,"sublayerTransform":[1,0,0,0,0,1,0,0,0,0,1,-0.0004200949496013118,0,0,0,1],"contentsRect":{"y":0,"x":0,"width":1,"height":1},"opacity":1,"edgeAntialiasingMask":15,"height":900,"hidden":false,"anchorPoint":{"pointX":0.5,"pointY":0.5}},"layers":[{"animations":[],"layers":[],"initialState":{"affineTransform":[1,0,0,1,0,0],"masksToBounds":false,"rotation":0,"scale":1,"position":{"pointX":800,"pointY":450},"width":1600,"sublayerTransform":[1,0,0,0,0,1,0,0,0,0,1,0,0,0,0,1],"contentsRect":{"y":0,"x":0,"width":1,"height":1},"opacity":1,"edgeAntialiasingMask":0,"height":900,"hidden":false,"anchorPoint":{"pointX":0.5,"pointY":0.5}},"texture":"7EB294B38CCD0E207FFE294CDDE637E3"}]}]}}]}