{"assets":{"5A4A6CA15CF6B37C0EBB4369C1D26992":{"type":"texture","index":59,"assetRequest":{"type":"slide","state":"incoming","slide":"72A3D4EE-769A-4992-A523-743604A4AA70"},"url":"assets/5A4A6CA15CF6B37C0EBB4369C1D26992.svg","width":1600,"height":900},"20FF7CFF3F0AC16A2236768D45970823":{"type":"texture","index":58,"assetRequest":{"type":"slide","state":"outgoing","slide":"6AE60D93-DB0F-4B42-A3B2-D2DD86FC958C"},"url":"assets/20FF7CFF3F0AC16A2236768D45970823.svg","width":1600,"height":900}},"events":[{"effects":[{"beginTime":0,"baseLayer":{"animations":[],"initialState":{"affineTransform":[1,0,0,1,0,0],"masksToBounds":true,"rotation":0,"scale":1,"position":{"pointX":800,"pointY":450},"width":1600,"sublayerTransform":[1,0,0,0,0,1,0,0,0,0,1,0,0,0,0,1],"contentsRect":{"y":0,"x":0,"width":1,"height":1},"opacity":1,"edgeAntialiasingMask":0,"height":900,"hidden":false,"anchorPoint":{"pointX":0.5,"pointY":0.5}},"objectID":"0","layers":[{"animations":[],"initialState":{"affineTransform":[1,0,0,1,0,0],"masksToBounds":false,"rotation":0,"scale":1,"position":{"pointX":800,"pointY":450},"width":1600,"sublayerTransform":[1,0,0,0,0,1,0,0,0,0,1,-0.0004200949496013118,0,0,0,1],"contentsRect":{"y":0,"x":0,"width":1,"height":1},"opacity":1,"edgeAntialiasingMask":15,"height":900,"hidden":false,"anchorPoint":{"pointX":0.5,"pointY":0.5}},"layers":[{"animations":[],"layers":[],"initialState":{"affineTransform":[1,0,0,1,0,0],"masksToBounds":false,"rotation":0,"scale":1,"position":{"pointX":800,"pointY":450},"width":1600,"sublayerTransform":[1,0,0,0,0,1,0,0,0,0,1,0,0,0,0,1],"contentsRect":{"y":0,"x":0,"width":1,"height":1},"opacity":1,"edgeAntialiasingMask":0,"height":900,"hidden":false,"anchorPoint":{"pointX":0.5,"pointY":0.5}},"texture":"5A4A6CA15CF6B37C0EBB4369C1D26992"},{"animations":[{"from":{"scalar":false},"beginTime":0,"repeatCount":0,"fillMode":"both","property":"hidden","duration":0.01,"to":{"scalar":true}}],"layers":[],"initialState":{"affineTransform":[1,0,0,1,0,0],"masksToBounds":false,"rotation":0,"scale":1,"position":{"pointX":800,"pointY":450},"width":1600,"sublayerTransform":[1,0,0,0,0,1,0,0,0,0,1,0,0,0,0,1],"contentsRect":{"y":0,"x":0,"width":1,"height":1},"opacity":1,"edgeAntialiasingMask":0,"height":900,"hidden":false,"anchorPoint":{"pointX":0.5,"pointY":0.5}},"texture":"20FF7CFF3F0AC16A2236768D45970823"}]}]},"effects":[],"duration":0.01,"type":"transition","name":"none","objectID":"0"}],"automaticPlay":false,"hyperlinks":[],"accessibility":[{"text":"14","targetRectangle":{"y":854.9642333984375,"x":1487.229248046875,"width":22.763671875,"height":21}},{"text":"GDS","targetRectangle":{"y":826,"x":1418.986328125,"width":91.013671875,"height":50}},{"text":"13","targetRectangle":{"y":854.9642333984375,"x":1487.229248046875,"width":22.763671875,"height":21}},{"text":"￼","targetRectangle":{"y":854.9642333984375,"x":1487.229248046875,"width":22.763671875,"height":21}},{"text":"Findings from user research highlight gaps in our understanding about the way people use computers","targetRectangle":{"y":304,"x":93,"width":1120.44,"height":216.0009155273438}}],"baseLayer":{"animations":[],"initialState":{"affineTransform":[1,0,0,1,0,0],"masksToBounds":true,"rotation":0,"scale":1,"position":{"pointX":800,"pointY":450},"width":1600,"sublayerTransform":[1,0,0,0,0,1,0,0,0,0,1,0,0,0,0,1],"contentsRect":{"y":0,"x":0,"width":1,"height":1},"opacity":1,"edgeAntialiasingMask":0,"height":900,"hidden":false,"anchorPoint":{"pointX":0.5,"pointY":0.5}},"objectID":"0","layers":[{"animations":[],"initialState":{"affineTransform":[1,0,0,1,0,0],"masksToBounds":false,"rotation":0,"scale":1,"position":{"pointX":800,"pointY":450},"width":1600,"sublayerTransform":[1,0,0,0,0,1,0,0,0,0,1,-0.0004200949496013118,0,0,0,1],"contentsRect":{"y":0,"x":0,"width":1,"height":1},"opacity":1,"edgeAntialiasingMask":15,"height":900,"hidden":false,"anchorPoint":{"pointX":0.5,"pointY":0.5}},"layers":[{"animations":[],"layers":[],"initialState":{"affineTransform":[1,0,0,1,0,0],"masksToBounds":false,"rotation":0,"scale":1,"position":{"pointX":800,"pointY":450},"width":1600,"sublayerTransform":[1,0,0,0,0,1,0,0,0,0,1,0,0,0,0,1],"contentsRect":{"y":0,"x":0,"width":1,"height":1},"opacity":1,"edgeAntialiasingMask":0,"height":900,"hidden":false,"anchorPoint":{"pointX":0.5,"pointY":0.5}},"texture":"20FF7CFF3F0AC16A2236768D45970823"}]}]}}]}